ptws_cli/__init__.py
ptws_cli-0.0.1.dist-info/licenses/LICENSE
ptws_cli-0.0.1.dist-info/METADATA
ptws_cli-0.0.1.dist-info/WHEEL
ptws_cli-0.0.1.dist-info/top_level.txt
ptws_cli-0.0.1.dist-info/RECORD
