Metadata-Version: 2.4
Name: ptws-cli
Version: 0.0.1
Summary: Placeholder alias for the PenTest.WS CLI. Install `ptws` (pulled automatically).
Author-email: "PenTest.WS" <support@pentest.ws>
Project-URL: Homepage, https://pentest.ws
Project-URL: Source, https://github.com/PenTestWS
Classifier: Programming Language :: Python :: 3
Classifier: License :: OSI Approved :: MIT License
Classifier: Development Status :: 3 - Alpha
Classifier: Intended Audience :: Information Technology
Classifier: Topic :: Security
Requires-Python: >=3.10
License-File: LICENSE
Requires-Dist: ptws>=0.0.1
Dynamic: license-file
